buildbot_legacy_slack_adapter/__init__.py
buildbot_legacy_slack_adapter/reporter.py
buildbot_legacy_slack_adapter-1.0.1.dist-info/LICENSE
buildbot_legacy_slack_adapter-1.0.1.dist-info/METADATA
buildbot_legacy_slack_adapter-1.0.1.dist-info/WHEEL
buildbot_legacy_slack_adapter-1.0.1.dist-info/entry_points.txt
buildbot_legacy_slack_adapter-1.0.1.dist-info/top_level.txt
buildbot_legacy_slack_adapter-1.0.1.dist-info/RECORD
