Metadata-Version: 2.1
Name: buildbot-legacy-slack-adapter
Version: 1.0.1
Summary: Plugin for integration with Slack on BuildBot 1.3.0.
Home-page: UNKNOWN
Author: Marc Leonardi
Author-email: marc@goodbarber.com
License: UNKNOWN
Platform: UNKNOWN
Classifier: Programming Language :: Python :: 3
Classifier: License :: OSI Approved :: MIT License
Classifier: Operating System :: OS Independent
Requires-Dist: buildbot (==1.3.0)
